getsmarter_api_clients/__init__.py
getsmarter_api_clients/geag.py
getsmarter_api_clients/oauth.py
getsmarter_api_clients-0.6.3.dist-info/licenses/LICENSE.txt
getsmarter_api_clients-0.6.3.dist-info/METADATA
getsmarter_api_clients-0.6.3.dist-info/WHEEL
getsmarter_api_clients-0.6.3.dist-info/top_level.txt
getsmarter_api_clients-0.6.3.dist-info/RECORD
