Metadata-Version: 2.4
Name: getsmarter-api-clients
Version: 0.6.3
Summary: Clients to interact with GetSmarter APIs.
Home-page: https://github.com/edx/getsmarter-api-clients
Author: edX
Author-email: oscm@edx.org
License: AGPL 3.0
Keywords: Python edx
Classifier: Development Status :: 3 - Alpha
Classifier: Intended Audience :: Developers
Classifier: License :: OSI Approved :: GNU Affero General Public License v3 or later (AGPLv3+)
Classifier: Natural Language :: English
Classifier: Programming Language :: Python :: 3
Classifier: Programming Language :: Python :: 3.12
Requires-Python: >3.8
License-File: LICENSE.txt
Requires-Dist: edx_django_utils
Requires-Dist: oauthlib
Requires-Dist: pytz
Requires-Dist: requests_oauthlib
Dynamic: author
Dynamic: author-email
Dynamic: classifier
Dynamic: description
Dynamic: home-page
Dynamic: keywords
Dynamic: license
Dynamic: license-file
Dynamic: requires-dist
Dynamic: requires-python
Dynamic: summary
